CHANGES.rst
CREDITS.rst
LICENSE.rst
MANIFEST.in
README.rst
setup.cfg
setup.py
lizard_structure/__init__.py
lizard_structure/admin.py
lizard_structure/models.py
lizard_structure/tests.py
lizard_structure/testsettings.py
lizard_structure/urls.py
lizard_structure/views.py
lizard_structure.egg-info/PKG-INFO
lizard_structure.egg-info/SOURCES.txt
lizard_structure.egg-info/dependency_links.txt
lizard_structure.egg-info/entry_points.txt
lizard_structure.egg-info/not-zip-safe
lizard_structure.egg-info/requires.txt
lizard_structure.egg-info/top_level.txt
lizard_structure/fixtures/README.rst
lizard_structure/static/lizard_structure/README.rst
lizard_structure/templates/lizard_structure/README.rst