Metadata-Version: 1.0
Name: lizard-structure
Version: 0.1
Summary: Structure of Lizard, defined and documented in a REST interface
Home-page: https://github.com/lizardsystem/lizard-structure
Author: Reinout van Rees
Author-email: reinout.vanrees@nelen-schuurmans.nl
License: GPL
Platform: UNKNOWN
Classifier: Programming Language :: Python
Classifier: Framework :: Django
